connection_utils/__init__.py
connection_utils/resource_mgr_connection.py
connection_utils/server_connection.py
connection_utils/server_resolver.py
gRPC_impl/__init__.py
gRPC_impl/shared_msg_types_pb2.py
gRPC_impl/shared_msg_types_pb2.pyi
gRPC_impl/shared_msg_types_pb2_grpc.py
gRPC_impl/mytorch/__init__.py
gRPC_impl/mytorch/mytorch_pb2.py
gRPC_impl/mytorch/mytorch_pb2.pyi
gRPC_impl/mytorch/mytorch_pb2_grpc.py
gRPC_impl/mytorch/tensor_pb2.py
gRPC_impl/mytorch/tensor_pb2.pyi
gRPC_impl/mytorch/tensor_pb2_grpc.py
gRPC_impl/mytorch/cacheq/__init__.py
gRPC_impl/mytorch/cacheq/cacheq_pb2.py
gRPC_impl/mytorch/cacheq/cacheq_pb2.pyi
gRPC_impl/mytorch/cacheq/cacheq_pb2_grpc.py
gRPC_impl/mytorch/cacheq/data_mgmt_pb2.py
gRPC_impl/mytorch/cacheq/data_mgmt_pb2.pyi
gRPC_impl/mytorch/cacheq/data_mgmt_pb2_grpc.py
gRPC_impl/mytorch/cacheq/resource_mgmt_pb2.py
gRPC_impl/mytorch/cacheq/resource_mgmt_pb2.pyi
gRPC_impl/mytorch/cacheq/resource_mgmt_pb2_grpc.py
gRPC_impl/mytorch/cacheq/server_mgmt_pb2.py
gRPC_impl/mytorch/cacheq/server_mgmt_pb2.pyi
gRPC_impl/mytorch/cacheq/server_mgmt_pb2_grpc.py
gRPC_impl/mytorch/cuda/__init__.py
gRPC_impl/mytorch/cuda/cuda_pb2.py
gRPC_impl/mytorch/cuda/cuda_pb2.pyi
gRPC_impl/mytorch/cuda/cuda_pb2_grpc.py
gRPC_impl/mytorch/hub/__init__.py
gRPC_impl/mytorch/hub/hub_pb2.py
gRPC_impl/mytorch/hub/hub_pb2.pyi
gRPC_impl/mytorch/hub/hub_pb2_grpc.py
gRPC_impl/mytorch/jit/__init__.py
gRPC_impl/mytorch/jit/jit_pb2.py
gRPC_impl/mytorch/jit/jit_pb2.pyi
gRPC_impl/mytorch/jit/jit_pb2_grpc.py
gRPC_impl/mytorch/nn/__init__.py
gRPC_impl/mytorch/nn/loss_functions_pb2.py
gRPC_impl/mytorch/nn/loss_functions_pb2.pyi
gRPC_impl/mytorch/nn/loss_functions_pb2_grpc.py
gRPC_impl/mytorch/nn/module_pb2.py
gRPC_impl/mytorch/nn/module_pb2.pyi
gRPC_impl/mytorch/nn/module_pb2_grpc.py
gRPC_impl/mytorch/nn/nn_msg_types_pb2.py
gRPC_impl/mytorch/nn/nn_msg_types_pb2.pyi
gRPC_impl/mytorch/nn/nn_msg_types_pb2_grpc.py
gRPC_impl/mytorch/nn/sequential_pb2.py
gRPC_impl/mytorch/nn/sequential_pb2.pyi
mytorch123-0.3.1.dist-info/METADATA
mytorch123-0.3.1.dist-info/WHEEL
mytorch123-0.3.1.dist-info/top_level.txt
mytorch123-0.3.1.dist-info/RECORD
